samep/__init__.py
samep/extension.py
samep/cogs/__init__.py
samep/cogs/event.py
samep/cogs/matching.py
samep/cogs/paneru.py
samep/cogs/reaction.py
samep/cogs/setting.py
samep/cogs/utils/__init__.py
samep/cogs/utils/datas.py
samep/cogs/utils/dget.py
samep/cogs/utils/embed.py
samep/cogs/utils/err.py
samep/cogs/utils/help.py
samep/cogs/utils/keys.py
samep/cogs/utils/paid.py
samep/cogs/utils/perms.py
samep/cogs/utils/webhooks.py
samep-0.0.5.dist-info/METADATA
samep-0.0.5.dist-info/WHEEL
samep-0.0.5.dist-info/top_level.txt
samep-0.0.5.dist-info/RECORD
