Metadata-Version: 2.1
Name: samep
Version: 0.0.5
Summary: samebotのplugin
Home-page: https://github.com/furimu1234/same/tree/main/utils
Author: furimu
License: UNKNOWN
Platform: UNKNOWN
Classifier: Programming Language :: Python :: 3.8
Classifier: License :: OSI Approved :: MIT License
Classifier: Operating System :: OS Independent
Requires-Dist: asyncpgw
Requires-Dist: discord.py
Requires-Dist: emoji
Requires-Dist: attrdict
